Metadata-Version: 2.1
Name: AskioCircleLib
Version: 0.0.3
Summary: circle class
Home-page: 
Author: Askio
Author-email: legoask@gmail.com
Keywords: circle
